{
  "V1_CASR": {
    "42": {
      "Common": {
        "csr": 88.796,
        "tpi": 40.815
      },
      "Significant": {
        "csr": 95.626,
        "tpi": 37.021
      },
      "Random": {
        "csr": 89.199,
        "tpi": 40.552
      }
    },
    "123": {
      "Common": {
        "csr": 90.989,
        "tpi": 39.845
      },
      "Significant": {
        "csr": 83.726,
        "tpi": 42.312
      },
      "Random": {
        "csr": 89.286,
        "tpi": 40.504
      }
    },
    "456": {
      "Common": {
        "csr": 89.146,
        "tpi": 40.661
      },
      "Significant": {
        "csr": 95.238,
        "tpi": 37.194
      },
      "Random": {
        "csr": 90.169,
        "tpi": 40.123
      }
    }
  },
  "V2_SAC_Only": {
    "42": {
      "Common": {
        "csr": 78.061,
        "tpi": 45.664
      },
      "Significant": {
        "csr": 78.206,
        "tpi": 44.824
      },
      "Random": {
        "csr": 80.037,
        "tpi": 44.658
      }
    },
    "123": {
      "Common": {
        "csr": 71.017,
        "tpi": 48.864
      },
      "Significant": {
        "csr": 74.953,
        "tpi": 46.29
      },
      "Random": {
        "csr": 73.642,
        "tpi": 47.529
      }
    },
    "456": {
      "Common": {
        "csr": 87.47,
        "tpi": 41.406
      },
      "Significant": {
        "csr": 83.292,
        "tpi": 42.511
      },
      "Random": {
        "csr": 87.258,
        "tpi": 41.434
      }
    }
  },
  "V3_Transformer_PPO": {
    "42": {
      "Common": {
        "csr": 91.314,
        "tpi": 39.692
      },
      "Significant": {
        "csr": 94.253,
        "tpi": 37.59
      },
      "Random": {
        "csr": 70.69800000000001,
        "tpi": 48.857
      }
    },
    "123": {
      "Common": {
        "csr": 86.071,
        "tpi": 42.032
      },
      "Significant": {
        "csr": 94.112,
        "tpi": 37.665
      },
      "Random": {
        "csr": 72.60799999999999,
        "tpi": 47.999
      }
    },
    "456": {
      "Common": {
        "csr": 72.108,
        "tpi": 48.371
      },
      "Significant": {
        "csr": 75.519,
        "tpi": 46.032
      },
      "Random": {
        "csr": 68.94,
        "tpi": 49.64
      }
    }
  },
  "V4_Full_TASCAR": {
    "42": {
      "Common": {
        "csr": 72.146,
        "tpi": 48.36
      },
      "Significant": {
        "csr": 75.521,
        "tpi": 46.031
      },
      "Random": {
        "csr": 68.95,
        "tpi": 49.637
      }
    },
    "123": {
      "Common": {
        "csr": 72.111,
        "tpi": 48.369
      },
      "Significant": {
        "csr": 75.521,
        "tpi": 46.031
      },
      "Random": {
        "csr": 68.94,
        "tpi": 49.64
      }
    },
    "456": {
      "Common": {
        "csr": 72.114,
        "tpi": 48.368
      },
      "Significant": {
        "csr": 75.52499999999999,
        "tpi": 46.029
      },
      "Random": {
        "csr": 68.94,
        "tpi": 49.64
      }
    }
  }
}